auto_ss.py
auto_ss-0.1.3.dist-info/DESCRIPTION.rst
auto_ss-0.1.3.dist-info/entry_points.txt
auto_ss-0.1.3.dist-info/METADATA
auto_ss-0.1.3.dist-info/metadata.json
auto_ss-0.1.3.dist-info/RECORD
auto_ss-0.1.3.dist-info/top_level.txt
auto_ss-0.1.3.dist-info/WHEEL
