Metadata-Version: 2.0
Name: auto-ss
Version: 0.1.3
Summary: Auto acquire ss-link free shadowsocks accounts and test connection speed
Home-page: https://github.com/steven-hl/ss-link-auto
Author: Steven Han
Author-email: steven.hl.0901@gmail.com
License: ISC
Platform: UNKNOWN
Requires-Dist: requests (==2.7.0)
Requires-Dist: requesocks (==0.10.8)
Requires-Dist: beautifulsoup4 (==4.3.2)
